[
  {
    "id": "cp_known_000",
    "item_a": "CN V (Trigeminal)",
    "item_b": "CN VII (Facial)",
    "topic_id": "head_neck",
    "confusion_count": 0,
    "total_encounters": 0,
    "confusion_rate": 0.0,
    "comparison_notes": "V=감각+저작근, VII=표정근+미각(전2/3)+타액선. V3와 VII 모두 귀 주변 지나감",
    "is_auto_detected": false,
    "last_seen_ts": null
  },
  {
    "id": "cp_known_001",
    "item_a": "CN IX (Glossopharyngeal)",
    "item_b": "CN X (Vagus)",
    "topic_id": "head_neck",
    "confusion_count": 0,
    "total_encounters": 0,
    "confusion_rate": 0.0,
    "comparison_notes": "IX=인두 감각+이하선+경동맥체, X=인두/후두 운동+부교감. 둘 다 경정맥공 통과",
    "is_auto_detected": false,
    "last_seen_ts": null
  },
  {
    "id": "cp_known_002",
    "item_a": "CN III (Oculomotor)",
    "item_b": "CN IV (Trochlear)",
    "topic_id": "head_neck",
    "confusion_count": 0,
    "total_encounters": 0,
    "confusion_rate": 0.0,
    "comparison_notes": "III=대부분 외안근+동공수축, IV=상사근만(SO4). III=상안와틈새, IV도 상안와틈새지만 유일한 배측 출현",
    "is_auto_detected": false,
    "last_seen_ts": null
  },
  {
    "id": "cp_known_003",
    "item_a": "CN XI (Accessory)",
    "item_b": "CN XII (Hypoglossal)",
    "topic_id": "head_neck",
    "confusion_count": 0,
    "total_encounters": 0,
    "confusion_rate": 0.0,
    "comparison_notes": "XI=SCM+Trapezius, XII=혀 근육. XI=경정맥공, XII=설하신경관",
    "is_auto_detected": false,
    "last_seen_ts": null
  },
  {
    "id": "cp_known_004",
    "item_a": "Corticospinal tract",
    "item_b": "Corticobulbar tract",
    "topic_id": "neuroanatomy",
    "confusion_count": 0,
    "total_encounters": 0,
    "confusion_rate": 0.0,
    "comparison_notes": "Spinal=사지/몸통 수의운동(연수 교차), Bulbar=뇌신경 운동핵으로(양측지배 많음)",
    "is_auto_detected": false,
    "last_seen_ts": null
  },
  {
    "id": "cp_known_005",
    "item_a": "Dorsal column pathway",
    "item_b": "Spinothalamic tract",
    "topic_id": "neuroanatomy",
    "confusion_count": 0,
    "total_encounters": 0,
    "confusion_rate": 0.0,
    "comparison_notes": "Dorsal=촉각+고유감각+진동(동측→연수교차), Spinothalamic=통각+온도(척수서 교차)",
    "is_auto_detected": false,
    "last_seen_ts": null
  },
  {
    "id": "cp_known_006",
    "item_a": "UMN lesion",
    "item_b": "LMN lesion",
    "topic_id": "neuroanatomy",
    "confusion_count": 0,
    "total_encounters": 0,
    "confusion_rate": 0.0,
    "comparison_notes": "UMN=경직마비+반사항진+바빈스키+, LMN=이완마비+반사감소+근위축+섬유속연축",
    "is_auto_detected": false,
    "last_seen_ts": null
  },
  {
    "id": "cp_known_007",
    "item_a": "Internal carotid a.",
    "item_b": "External carotid a.",
    "topic_id": "head_neck",
    "confusion_count": 0,
    "total_encounters": 0,
    "confusion_rate": 0.0,
    "comparison_notes": "Internal=뇌+안구(가지없이 올라감), External=얼굴+두피(8개 가지)",
    "is_auto_detected": false,
    "last_seen_ts": null
  },
  {
    "id": "cp_known_008",
    "item_a": "Middle cerebral a.",
    "item_b": "Anterior cerebral a.",
    "topic_id": "neuroanatomy",
    "confusion_count": 0,
    "total_encounters": 0,
    "confusion_rate": 0.0,
    "comparison_notes": "MCA=외측면(운동/감각 팔/얼굴, Broca/Wernicke), ACA=내측면(운동/감각 다리)",
    "is_auto_detected": false,
    "last_seen_ts": null
  },
  {
    "id": "cp_known_009",
    "item_a": "Vertebral a.",
    "item_b": "Basilar a.",
    "topic_id": "neuroanatomy",
    "confusion_count": 0,
    "total_encounters": 0,
    "confusion_rate": 0.0,
    "comparison_notes": "Vertebral=PICA+전척수동맥, Basilar=AICA+SCA+PCA. Vertebral 합쳐서 Basilar",
    "is_auto_detected": false,
    "last_seen_ts": null
  },
  {
    "id": "cp_known_010",
    "item_a": "Anterior triangle",
    "item_b": "Posterior triangle",
    "topic_id": "neck",
    "confusion_count": 0,
    "total_encounters": 0,
    "confusion_rate": 0.0,
    "comparison_notes": "전삼각=SCM전방(경동맥,뇌신경), 후삼각=SCM후방(부신경,상완신경총,쇄골하동맥)",
    "is_auto_detected": false,
    "last_seen_ts": null
  },
  {
    "id": "cp_known_011",
    "item_a": "Sympathetic",
    "item_b": "Parasympathetic",
    "topic_id": "neuroanatomy",
    "confusion_count": 0,
    "total_encounters": 0,
    "confusion_rate": 0.0,
    "comparison_notes": "교감=T1-L2, 짧은절전+긴절후, fight/flight. 부교감=CN III,VII,IX,X+S2-4, 긴절전+짧은절후, rest/digest",
    "is_auto_detected": false,
    "last_seen_ts": null
  },
  {
    "id": "cp_known_012",
    "item_a": "Foramen rotundum",
    "item_b": "Foramen ovale",
    "topic_id": "head_neck",
    "confusion_count": 0,
    "total_encounters": 0,
    "confusion_rate": 0.0,
    "comparison_notes": "Rotundum=V2(상악신경), Ovale=V3(하악신경). 둘 다 중두개와→익구개와/측두하와",
    "is_auto_detected": false,
    "last_seen_ts": null
  },
  {
    "id": "cp_known_013",
    "item_a": "Superior orbital fissure",
    "item_b": "Inferior orbital fissure",
    "topic_id": "head_neck",
    "confusion_count": 0,
    "total_encounters": 0,
    "confusion_rate": 0.0,
    "comparison_notes": "SOF=CN III,IV,V1,VI+안정맥, IOF=V2+하안정맥. SOF=중두개와↔안와, IOF=익구개와↔안와",
    "is_auto_detected": false,
    "last_seen_ts": null
  },
  {
    "id": "cp_known_014",
    "item_a": "Broca area",
    "item_b": "Wernicke area",
    "topic_id": "neuroanatomy",
    "confusion_count": 0,
    "total_encounters": 0,
    "confusion_rate": 0.0,
    "comparison_notes": "Broca=전두엽(44,45)=운동실어증(비유창), Wernicke=측두엽(22)=감각실어증(유창하지만 무의미)",
    "is_auto_detected": false,
    "last_seen_ts": null
  },
  {
    "id": "cp_known_015",
    "item_a": "Recurrent laryngeal n.",
    "item_b": "Superior laryngeal n.",
    "topic_id": "ear_pharynx_larynx",
    "confusion_count": 0,
    "total_encounters": 0,
    "confusion_rate": 0.0,
    "comparison_notes": "RLN(=inferior)=후두 대부분 운동+성문하 감각, SLN 외지=윤상갑상근, SLN 내지=성문상 감각",
    "is_auto_detected": false,
    "last_seen_ts": null
  }
]